<?xml version='1.0' encoding='UTF-8'?>
<!DOCTYPE preface PUBLIC "-//OASIS//DTD DocBook XML V4.4//EN"
  "http://www.oasis-open.org/docbook/xml/4.4/docbookx.dtd">

<preface id="preface">
<title>序文</title>

<para>
OTRS 管理者向けの冊子です。OTRS 初心者のための参考書としても提供しています。
</para>

<para>
次の章では、インストール、構成、および OTRS ソフトウェアの管理について説明します。テキストの最初の
3行で、ソフトウェアの主要な機能について説明しています。一方残りの部分は、構成可能なパラメタの完全なセットへの参照として提供されています。
</para>

<para>
この本は、新しいリリースに向けて動的な目標を与えられ、常に進行中の作業として継続しています。使いやすく正確で完全な、高品質の参照ドキュメントを作るためにあなたのフィードバックを必要としています。もしご協力頂けるようでしたら感謝申し上げます。
</para>

</preface>
